pyoracle_forms/__init__.py
pyoracle_forms/constants.py
pyoracle_forms/context.py
pyoracle_forms/error_handling.py
pyoracle_forms/forms_api.py
pyoracle_forms/forms_objects.py
pyoracle_forms/generic_object.py
pyoracle_forms/misc.py
pyoracle_forms/property_types.py
pyoracle_forms/forms_api/parsed_10g.json
pyoracle_forms/forms_api/parsed_12c.json
pyoracle_forms/forms_api/parsed_6i.json
pyoracle_forms-0.5.2.dist-info/LICENSE
pyoracle_forms-0.5.2.dist-info/METADATA
pyoracle_forms-0.5.2.dist-info/WHEEL
pyoracle_forms-0.5.2.dist-info/top_level.txt
pyoracle_forms-0.5.2.dist-info/RECORD
