Metadata-Version: 2.1
Name: pyoracle_forms
Version: 0.5.2
Summary: Python wrapper of the Oracle Forms API
Home-page: https://github.com/LatvianPython/pyoracle_forms
Author: LatvianPython
Author-email: kalvans.rolands@gmail.com
Classifier: Programming Language :: Python :: 3.9
Classifier: Programming Language :: Python :: 3.10
Classifier: License :: OSI Approved :: MIT License
Classifier: Operating System :: Microsoft :: Windows
Classifier: Development Status :: 2 - Pre-Alpha
Requires-Python: >=3.9
License-File: LICENSE
